control_block_diagram/__init__.py
control_block_diagram/control_diagram.py
control_block_diagram/components/__init__.py
control_block_diagram/components/component.py
control_block_diagram/components/blocks/__init__.py
control_block_diagram/components/blocks/block.py
control_block_diagram/components/blocks/boxes/__init__.py
control_block_diagram/components/blocks/boxes/box.py
control_block_diagram/components/blocks/circles/__init__.py
control_block_diagram/components/blocks/circles/circle.py
control_block_diagram/components/blocks/custom_block/__init__.py
control_block_diagram/components/blocks/custom_block/custom_block.py
control_block_diagram/components/blocks/triangles/__init__.py
control_block_diagram/components/blocks/triangles/triangle.py
control_block_diagram/components/connections/__init__.py
control_block_diagram/components/connections/connection.py
control_block_diagram/components/connections/generate_connection.py
control_block_diagram/components/connections/path.py
control_block_diagram/components/points/__init__.py
control_block_diagram/components/points/center.py
control_block_diagram/components/points/input.py
control_block_diagram/components/points/output.py
control_block_diagram/components/points/point.py
control_block_diagram/components/text/__init__.py
control_block_diagram/components/text/text.py
control_block_diagram/pdf_viewer/__init__.py
control_block_diagram/pdf_viewer/pdf_viewer.py
control_block_diagram/pdf_viewer/pdf_viewer_nb.py
control_block_diagram/pdf_viewer/window.py
control_block_diagram/predefined_components/__init__.py
control_block_diagram/predefined_components/predefined_components.py
control_block_diagram/predefined_components/control_blocks/__init__.py
control_block_diagram/predefined_components/control_blocks/i_controller.py
control_block_diagram/predefined_components/control_blocks/limit.py
control_block_diagram/predefined_components/control_blocks/pi_controller.py
control_block_diagram-0.0.1.dist-info/LICENSE
control_block_diagram-0.0.1.dist-info/METADATA
control_block_diagram-0.0.1.dist-info/WHEEL
control_block_diagram-0.0.1.dist-info/top_level.txt
control_block_diagram-0.0.1.dist-info/RECORD
