Metadata-Version: 2.1
Name: control-block-diagram
Version: 0.0.1
Summary: Python Toolbox to draw Control Block Diagrams
Home-page: https://github.com/upb-lea/control-block-diagram
Author: Felix Book
Author-email: Felix Book <64723297+fbook98@users.noreply.github.com>
Project-URL: Homepage, https://github.com/upb-lea/control-block-diagram
Project-URL: Bug Tracker, https://github.com/upb-lea/control-block-diagram/issues
Classifier: Programming Language :: Python :: 3
Classifier: License :: OSI Approved :: MIT License
Classifier: Operating System :: OS Independent
Requires-Python: >=3.6
License-File: LICENSE
Requires-Dist: matplotlib (>=3.1.2)
Requires-Dist: numpy (>=1.16.4)
Requires-Dist: pylatex (>=1.4.1)
Requires-Dist: pyqt5 (>=5.15.6)
Requires-Dist: pyqtwebengine (>=5.15.5)
